MANIFEST.in
README.rst
setup.cfg
setup.py
apex/__init__.py
apex/decorators.py
apex/exceptions.py
apex/forms.py
apex/i18n.py
apex/interfaces.py
apex/models.py
apex/views.py
apex.egg-info/PKG-INFO
apex.egg-info/SOURCES.txt
apex.egg-info/dependency_links.txt
apex.egg-info/entry_points.txt
apex.egg-info/requires.txt
apex.egg-info/top_level.txt
apex.egg-info/zip-safe
apex/ext/__init__.py
apex/ext/deform.py
apex/lib/__init__.py
apex/lib/db.py
apex/lib/fallbacks.py
apex/lib/flash.py
apex/lib/form.py
apex/lib/i18n.py
apex/lib/libapex.py
apex/lib/subscribers.py
apex/locale/apex.pot
apex/locale/fr/LC_MESSAGES/Apex.mo
apex/locale/fr/LC_MESSAGES/Apex.po
apex/scaffolds/__init__.py
apex/static/css/apex_flash.css
apex/static/css/apex_forms.css
apex/static/images/fb-connect.png
apex/static/images/google-connect.png
apex/static/images/twitter-connect.png
apex/templates/apex_callback.mako
apex/templates/apex_template.mako
apex/templates/apex_template.pt
apex/templates/flash_template.jinja2
apex/templates/flash_template.mako
apex/templates/flash_template.pt
apex/templates/login_template.mako
apex/templates/forms/fieldsetform.mako
apex/templates/forms/tableform.mako
apex/templates/forms/tableform.pt
apex/tests/__init__.py
apex/tests/test_lib_libapex.py
apex/tests/test_views.py