Metadata-Version: 1.1
Name: apex
Version: 0.9.10dev
Summary: Pyramid toolkit to add Velruse, Flash Messages,CSRF, ReCaptcha and Sessions
Home-page: http://thesoftwarestudio.com/apex/
Author: Chris Davies
Author-email: user@domain.com
License: MIT
Platform: UNKNOWN
Classifier: Intended Audience :: Developers
Classifier: Programming Language :: Python
Classifier: License :: OSI Approved :: MIT License
